ipykernel_helper/__init__.py
ipykernel_helper/_modidx.py
ipykernel_helper/core.py
ipykernel_helper-0.0.28.dist-info/licenses/LICENSE
ipykernel_helper-0.0.28.dist-info/METADATA
ipykernel_helper-0.0.28.dist-info/WHEEL
ipykernel_helper-0.0.28.dist-info/entry_points.txt
ipykernel_helper-0.0.28.dist-info/top_level.txt
ipykernel_helper-0.0.28.dist-info/RECORD
