Metadata-Version: 2.4
Name: ipykernel-helper
Version: 0.0.28
Summary: Helpers for ipykernel and friends
Home-page: https://github.com/AnswerDotAI/ipykernel-helper
Author: Jeremy Howard
Author-email: info@fast.ai
License: Apache Software License 2.0
Keywords: nbdev jupyter notebook python
Classifier: Development Status :: 4 - Beta
Classifier: Intended Audience :: Developers
Classifier: Natural Language :: English
Classifier: Programming Language :: Python :: 3.9
Classifier: Programming Language :: Python :: 3.10
Classifier: Programming Language :: Python :: 3.11
Classifier: Programming Language :: Python :: 3.12
Classifier: License :: OSI Approved :: Apache Software License
Requires-Python: >=3.9
License-File: LICENSE
Requires-Dist: fastcore>=1.12.2
Requires-Dist: toolslm>=0.3.13
Requires-Dist: jedi
Requires-Dist: ipython
Requires-Dist: ipykernel
Requires-Dist: beautifulsoup4
Requires-Dist: lxml
Requires-Dist: html2text
Requires-Dist: cloudscraper
Requires-Dist: ghapi
Provides-Extra: dev
Dynamic: author
Dynamic: author-email
Dynamic: classifier
Dynamic: description
Dynamic: description-content-type
Dynamic: home-page
Dynamic: keywords
Dynamic: license
Dynamic: license-file
Dynamic: provides-extra
Dynamic: requires-dist
Dynamic: requires-python
Dynamic: summary
